pubmedpy/__init__.py
pubmedpy/eutilities.py
pubmedpy/test_extraction.py
pubmedpy/xml_to_dates.py
pubmedpy-0.0.0.dist-info/METADATA
pubmedpy-0.0.0.dist-info/WHEEL
pubmedpy-0.0.0.dist-info/top_level.txt
pubmedpy-0.0.0.dist-info/RECORD
